[
  {
    "timecode": "00:29",
    "speaker": "",
    "quote": "",
    "directions": [
      "LAW FIRM: INT. LAW FIRM - MR. DEWEY'S OFFICE - SIMULTANEOUS"
    ],
    "raw_quote": "(LAW FIRM: INT. LAW FIRM - MR. DEWEY'S OFFICE - SIMULTANEOUS)"
  },
  {
    "timecode": "00:29",
    "speaker": "Mr. Dewey",
    "quote": " May I offer my condolences on the untimely passing of your Great Aunt Hortense. As her only living heirs, you stand to inherit her entire estate.",
    "directions": [
      "MORTICIAN'S DEMEANOR"
    ],
    "raw_quote": " (MORTICIAN'S DEMEANOR) May I offer my condolences on the untimely passing of your Great Aunt Hortense. As her only living heirs, you stand to inherit her entire estate."
  },
  {
    "timecode": "00:39",
    "speaker": "Homer Simpson",
    "quote": " Poor Aunt Hortense... woo-hoo... woo-hoo...",
    "directions": [
      "CRYING",
      "SOBS",
      "SOBS"
    ],
    "raw_quote": " (CRYING) Poor Aunt Hortense... (SOBS) woo-hoo... (SOBS) woo-hoo..."
  },
  {
    "timecode": "00:46",
    "speaker": "Mr. Dewey",
    "quote": " The only stipulation is that you spend one night in a haunted house.",
    "directions": [
      "OMINOUS"
    ],
    "raw_quote": " (OMINOUS) The only stipulation is that you spend one night in a haunted house."
  },
  {
    "timecode": "00:52",
    "speaker": "Marge Simpson",
    "quote": " Oh, isn't that somewhat unusual?",
    "directions": [],
    "raw_quote": " Oh, isn't that somewhat unusual?"
  },
  {
    "timecode": "00:53",
    "speaker": "Mr. Dewey",
    "quote": " No, it's a standard clause.",
    "directions": [],
    "raw_quote": " No, it's a standard clause."
  },
  {
    "timecode": "00:56",
    "speaker": "Homer Simpson",
    "quote": " Well, luckily, there's no such thing as ghosts.",
    "directions": [
      "CONFIDENT, TO FAMILY"
    ],
    "raw_quote": " (CONFIDENT, TO FAMILY) Well, luckily, there's no such thing as ghosts."
  },
  {
    "timecode": "01:03",
    "speaker": "",
    "quote": "",
    "directions": [
      "Haunted House: EXT. HAUNTED HOUSE - THAT NIGHT"
    ],
    "raw_quote": "(Haunted House: EXT. HAUNTED HOUSE - THAT NIGHT)"
  },
  {
    "timecode": "01:03",
    "speaker": "Homer Simpson",
    "quote": " Yes, there's no such thing as ghosts.",
    "directions": [
      "HAPPILY, TO HIMSELF"
    ],
    "raw_quote": " (HAPPILY, TO HIMSELF) Yes, there's no such thing as ghosts."
  },
  {
    "timecode": "01:17",
    "speaker": "Homer Simpson",
    "quote": " Best night's sleep I ever had.",
    "directions": [
      "STRETCHING"
    ],
    "raw_quote": " (STRETCHING) Best night's sleep I ever had."
  },
  {
    "timecode": "01:19",
    "speaker": "Lisa Simpson",
    "quote": " Their tap water tasted better than ours!",
    "directions": [],
    "raw_quote": " Their tap water tasted better than ours!"
  },
  {
    "timecode": "01:22",
    "speaker": "Mr. Dewey",
    "quote": " Here you go. One hundred dollars each... The rest goes to Ann Landers, as was stipulated in your aunt's will.",
    "directions": [],
    "raw_quote": " Here you go. One hundred dollars each... The rest goes to Ann Landers, as was stipulated in your aunt's will."
  },
  {
    "timecode": "",
    "speaker": "Lisa Simpson",
    "quote": " ",
    "directions": [
      "CLOSED-MOUTHED SOUNDS OF DISBELIEF"
    ],
    "raw_quote": " (CLOSED-MOUTHED SOUNDS OF DISBELIEF)"
  },
  {
    "timecode": "01:31",
    "speaker": "Mr. Dewey",
    "quote": " Oh, I'm sorry, I must have continued talking after you left the office. I do that sometimes. ",
    "directions": [
      "OFF THEIR STUNNED LOOKS",
      "DIABOLICAL LAUGH"
    ],
    "raw_quote": " (OFF THEIR STUNNED LOOKS) Oh, I'm sorry, I must have continued talking after you left the office. I do that sometimes. (DIABOLICAL LAUGH)"
  },
  {
    "timecode": "01:45",
    "speaker": "",
    "quote": "",
    "directions": [
      "Simpson Car: INT. SIMPSON CAR - A FEW MINUTES LATER"
    ],
    "raw_quote": "(Simpson Car: INT. SIMPSON CAR - A FEW MINUTES LATER)"
  },
  {
    "timecode": "01:45",
    "speaker": "Marge Simpson",
    "quote": " What are you going to spend your money on, kids?",
    "directions": [],
    "raw_quote": " What are you going to spend your money on, kids?"
  },
  {
    "timecode": "01:47",
    "speaker": "Bart Simpson",
    "quote": " There's a special on tacos down at the The TacoMat. A hundred tacos for a hundred dollars. I'm gonna get that.",
    "directions": [],
    "raw_quote": " There's a special on tacos down at the The TacoMat. A hundred tacos for a hundred dollars. I'm gonna get that."
  },
  {
    "timecode": "01:52",
    "speaker": "Lisa Simpson",
    "quote": " I'm going to contribute my money to the Corporation for Public Broadcasting.",
    "directions": [],
    "raw_quote": " I'm going to contribute my money to the Corporation for Public Broadcasting."
  },
  {
    "timecode": "01:55",
    "speaker": "Marge Simpson",
    "quote": " Tacos! Public Broadcasting! I won't have you kids throwing your money away like that. You're both coming downtown with me and you're gonna put that money in the bank.",
    "directions": [],
    "raw_quote": " Tacos! Public Broadcasting! I won't have you kids throwing your money away like that. You're both coming downtown with me and you're gonna put that money in the bank."
  },
  {
    "timecode": "02:10",
    "speaker": "",
    "quote": "",
    "directions": [
      "DOWNTOWN: EXT. DOWNTOWN - A LITTLE LATER"
    ],
    "raw_quote": "(DOWNTOWN: EXT. DOWNTOWN - A LITTLE LATER)"
  },
  {
    "timecode": "02:10",
    "speaker": "Bart Simpson",
    "quote": " Boy, I sure could go for a hundred tacos right about now.",
    "directions": [
      "HINTING"
    ],
    "raw_quote": " (HINTING) Boy, I sure could go for a hundred tacos right about now."
  },
  {
    "timecode": "02:13",
    "speaker": "Marge Simpson",
    "quote": " No.",
    "directions": [],
    "raw_quote": " No."
  },
  {
    "timecode": "02:15",
    "speaker": "Comic Book Guy",
    "quote": " Yes, this should provide adequate sustenance for the \"Dr. Who\" marathon.",
    "directions": [],
    "raw_quote": " Yes, this should provide adequate sustenance for the \"Dr. Who\" marathon."
  },
  {
    "timecode": "02:22",
    "speaker": "",
    "quote": "",
    "directions": [
      "First National Bank of Springfield: INT. FIRST NATIONAL BANK OF SPRINGFIELD - LOBBY - CONTINUOUS"
    ],
    "raw_quote": "(First National Bank of Springfield: INT. FIRST NATIONAL BANK OF SPRINGFIELD - LOBBY - CONTINUOUS)"
  },
  {
    "timecode": "02:22",
    "speaker": "Marge Simpson",
    "quote": " You'll feel better knowing your money's in the hands of professionals.",
    "directions": [],
    "raw_quote": " You'll feel better knowing your money's in the hands of professionals."
  },
  {
    "timecode": "02:25",
    "speaker": "Teller",
    "quote": " Ook, ook. Are you folks ready to go ape?",
    "directions": [
      "MUFFLED BY APE MASK"
    ],
    "raw_quote": " (MUFFLED BY APE MASK) Ook, ook. Are you folks ready to go ape?"
  },
  {
    "timecode": "02:28",
    "speaker": "Lisa Simpson",
    "quote": " Mom?",
    "directions": [],
    "raw_quote": " Mom?"
  },
  {
    "timecode": "02:29",
    "speaker": "Marge Simpson",
    "quote": " A professional in an ape mask is still a professional.",
    "directions": [],
    "raw_quote": " A professional in an ape mask is still a professional."
  },
  {
    "timecode": "02:32",
    "speaker": "Bank Employee",
    "quote": " ... and you'll find that saving for your future is far more thrilling than any rollercoaster.",
    "directions": [],
    "raw_quote": " ... and you'll find that saving for your future is far more thrilling than any rollercoaster."
  },
  {
    "timecode": "02:38",
    "speaker": "Bart Simpson",
    "quote": " Really?! Wow, I should've started a long time ago!",
    "directions": [],
    "raw_quote": " Really?! Wow, I should've started a long time ago!"
  },
  {
    "timecode": "02:41",
    "speaker": "Bank Employee",
    "quote": " Mmm-hmm. Now fill out these forms. I'm sure you'll find them more exciting than a weekend with Batman.",
    "directions": [],
    "raw_quote": " Mmm-hmm. Now fill out these forms. I'm sure you'll find them more exciting than a weekend with Batman."
  },
  {
    "timecode": "02:48",
    "speaker": "",
    "quote": "",
    "directions": [
      "Simpson Car: INT. SIMPSON CAR - A LITTLE LATER"
    ],
    "raw_quote": "(Simpson Car: INT. SIMPSON CAR - A LITTLE LATER)"
  },
  {
    "timecode": "02:48",
    "speaker": "Lisa Simpson",
    "quote": " I got their new Thrifty Saver Savings account. 2.3% annual interest instead of the normal 2.25. So a year from now I'll have an extra nickel.",
    "directions": [
      "EXCITED"
    ],
    "raw_quote": " (EXCITED) I got their new Thrifty Saver Savings account. 2.3% annual interest instead of the normal 2.25. So a year from now I'll have an extra nickel."
  },
  {
    "timecode": "02:56",
    "speaker": "Bart Simpson",
    "quote": " I got the account where you get free customized checks. I chose the Hindenberg flip-book series.",
    "directions": [],
    "raw_quote": " I got the account where you get free customized checks. I chose the Hindenberg flip-book series."
  },
  {
    "timecode": "03:01",
    "speaker": "Bart Simpson",
    "quote": " Coooool.",
    "directions": [],
    "raw_quote": " Coooool."
  },
  {
    "timecode": "03:03",
    "speaker": "Marge Simpson",
    "quote": " Checking accounts aren't really for children, Bart.",
    "directions": [
      "ANNOYED MURMUR"
    ],
    "raw_quote": " (ANNOYED MURMUR) Checking accounts aren't really for children, Bart."
  },
  {
    "timecode": "03:06",
    "speaker": "Bart Simpson",
    "quote": " No, Mom, I can handle it. Let's see... Pay to the order of... Lisa. One cent... and no cents. And now the old John Hancock... Here you go.",
    "directions": [
      "DEMONSTRATING",
      "WRITING"
    ],
    "raw_quote": " No, Mom, I can handle it. (DEMONSTRATING) Let's see... (WRITING) Pay to the order of... Lisa. One cent... and no cents. And now the old John Hancock... Here you go."
  },
  {
    "timecode": "03:18",
    "speaker": "Lisa Simpson",
    "quote": " Thank you.",
    "directions": [
      "BUSINESSLIKE"
    ],
    "raw_quote": " (BUSINESSLIKE) Thank you."
  },
  {
    "timecode": "03:19",
    "speaker": "",
    "quote": "",
    "directions": [
      "Springfield Elementary School: INT. SPRINGFIELD ELEMENTARY - BART'S CLASS - THE NEXT DAY"
    ],
    "raw_quote": "(Springfield Elementary School: INT. SPRINGFIELD ELEMENTARY - BART'S CLASS - THE NEXT DAY)"
  },
  {
    "timecode": "03:19",
    "speaker": "Milhouse Van Houten",
    "quote": " A million dollars! Thanks, Bart! I owe you one.",
    "directions": [],
    "raw_quote": " A million dollars! Thanks, Bart! I owe you one."
  },
  {
    "timecode": "03:23",
    "speaker": "Bart Simpson",
    "quote": " Uh, that's a post-dated check, remember. Don't cash it 'til the year ten thousand.",
    "directions": [],
    "raw_quote": " Uh, that's a post-dated check, remember. Don't cash it 'til the year ten thousand."
  },
  {
    "timecode": "03:26",
    "speaker": "Milhouse Van Houten",
    "quote": " Okay.",
    "directions": [],
    "raw_quote": " Okay."
  },
  {
    "timecode": "03:35",
    "speaker": "",
    "quote": "",
    "directions": [
      "Somewhere: Ext. somewhere"
    ],
    "raw_quote": "(Somewhere: Ext. somewhere)"
  },
  {
    "timecode": "03:35",
    "speaker": "Jimbo Jones",
    "quote": " Excellent. As soon as the check clears, I'll let you go.",
    "directions": [],
    "raw_quote": " Excellent. As soon as the check clears, I'll let you go."
  },
  {
    "timecode": "03:42",
    "speaker": "",
    "quote": "",
    "directions": [
      "Krustylu Studios: Ext. Krusty's studios - afternoon"
    ],
    "raw_quote": "(Krustylu Studios: Ext. Krusty's studios - afternoon)"
  },
  {
    "timecode": "03:42",
    "speaker": "Kids",
    "quote": " Can I get your autograph, Krusty? / Me first! / Me third! / etc.",
    "directions": [],
    "raw_quote": " Can I get your autograph, Krusty? / Me first! / Me third! / etc."
  },
  {
    "timecode": "03:45",
    "speaker": "Krusty the Clown",
    "quote": " That's it. No more autographs. I gotta go. They're naming a new sandwich after me at my restaurant.",
    "directions": [],
    "raw_quote": " That's it. No more autographs. I gotta go. They're naming a new sandwich after me at my restaurant."
  },
  {
    "timecode": "",
    "speaker": "Bart Simpson",
    "quote": " ",
    "directions": [
      "DISAPPOINTED NOISE"
    ],
    "raw_quote": " (DISAPPOINTED NOISE)"
  },
  {
    "timecode": "03:52",
    "speaker": "Milhouse Van Houten",
    "quote": " It's okay, Bart. You can share mine.",
    "directions": [],
    "raw_quote": " It's okay, Bart. You can share mine."
  },
  {
    "timecode": "03:54",
    "speaker": "Milhouse Van Houten",
    "quote": " Quick -- press against me while the ink's still wet!",
    "directions": [],
    "raw_quote": " Quick -- press against me while the ink's still wet!"
  },
  {
    "timecode": "03:57",
    "speaker": "Bart Simpson",
    "quote": " No need. I'm going to get Krusty's autograph the easy way.",
    "directions": [],
    "raw_quote": " No need. I'm going to get Krusty's autograph the easy way."
  },
  {
    "timecode": "04:01",
    "speaker": "Bart Simpson",
    "quote": " If he wants these 25 cents, he'll have to endorse the check by signing it on the back. Then when my monthly bank statement comes, I'll get the check back complete with autograph. No fuss, no muss.",
    "directions": [],
    "raw_quote": " If he wants these 25 cents, he'll have to endorse the check by signing it on the back. Then when my monthly bank statement comes, I'll get the check back complete with autograph. No fuss, no muss."
  },
  {
    "timecode": "04:14",
    "speaker": "Milhouse Van Houten",
    "quote": " That's a good plan. But it won't impress girls like this.",
    "directions": [],
    "raw_quote": " That's a good plan. But it won't impress girls like this."
  },
  {
    "timecode": "04:18",
    "speaker": "Girls",
    "quote": " Ewwww!",
    "directions": [],
    "raw_quote": " Ewwww!"
  },
  {
    "timecode": "",
    "speaker": "Milhouse Van Houten",
    "quote": " ",
    "directions": [
      "GOOFY CHUCKLE"
    ],
    "raw_quote": " (GOOFY CHUCKLE)"
  },
  {
    "timecode": "04:25",
    "speaker": "",
    "quote": "",
    "directions": [
      "Simpson Home: INT. SIMPSON HOUSE - BART'S ROOM - A MONTH LATER"
    ],
    "raw_quote": "(Simpson Home: INT. SIMPSON HOUSE - BART'S ROOM - A MONTH LATER)"
  },
  {
    "timecode": "04:25",
    "speaker": "Bart Simpson",
    "quote": " Lisa's autograph... Apu's autograph... Oh, whaddaya know, Jimbo's real name is Corky... Aannnnd Krusty... Hey! \"Cayman Islands Offshore Holding Corporation\"?",
    "directions": [
      "FLIPS CHECK OVER",
      "READING"
    ],
    "raw_quote": " Lisa's autograph... Apu's autograph... Oh, whaddaya know, Jimbo's real name is Corky... Aannnnd Krusty... (FLIPS CHECK OVER) Hey! (READING) \"Cayman Islands Offshore Holding Corporation\"?"
  },
  {
    "timecode": "04:41",
    "speaker": "",
    "quote": "",
    "directions": [
      "First National Bank of Springfield: ext. first national bank of springfield - day"
    ],
    "raw_quote": "(First National Bank of Springfield: ext. first national bank of springfield - day)"
  },
  {
    "timecode": "04:41",
    "speaker": "Bart Simpson",
    "quote": " Krusty was supposed to sign this. Take it back and make him sign it.",
    "directions": [],
    "raw_quote": " Krusty was supposed to sign this. Take it back and make him sign it."
  },
  {
    "timecode": "04:43",
    "speaker": "Teller #2",
    "quote": " Uh, no, no. Stamping the back of a check is perfectly legal, little boy. Many people do it to save time. You see in this case, instead of writing out his name, Krusty has stamped the name of his Cayman Islands holding corporation on... Hmm... excuse me a minute...",
    "directions": [
      "SUDDENLY SUSPICIOUS"
    ],
    "raw_quote": " Uh, no, no. Stamping the back of a check is perfectly legal, little boy. Many people do it to save time. You see in this case, instead of writing out his name, Krusty has stamped the name of his Cayman Islands holding corporation on... (SUDDENLY SUSPICIOUS) Hmm... excuse me a minute..."
  },
  {
    "timecode": "05:09",
    "speaker": "Cayman Islands Bank Guy",
    "quote": " Oh, I'm sorry. I can't divulge information about that customer's secret illegal account. Oh, crap, I shouldn't have said he was a customer... Oh, crap, I shouldn't have said it was a secret... Oh, crap, I certainly shouldn't have said it was illegal! It's too hot today.",
    "directions": [
      "SYDNEY GREENSTREET VOICE; CHUCKLES",
      "HANGS UP PHONE",
      "BEAT; SIGHS"
    ],
    "raw_quote": " (SYDNEY GREENSTREET VOICE; CHUCKLES) Oh, I'm sorry. I can't divulge information about that customer's secret illegal account. (HANGS UP PHONE) Oh, crap, I shouldn't have said he was a customer... Oh, crap, I shouldn't have said it was a secret... Oh, crap, I certainly shouldn't have said it was illegal! (BEAT; SIGHS) It's too hot today."
  },
  {
    "timecode": "05:38",
    "speaker": "Krusty the Clown",
    "quote": " Hey-hey-hey-hey-hey! I bought this popcorn fair and square!",
    "directions": [],
    "raw_quote": " Hey-hey-hey-hey-hey! I bought this popcorn fair and square!"
  },
  {
    "timecode": "05:43",
    "speaker": "Teller #2",
    "quote": " Sorry, the bank is close-- Oh, kid, gosh, I meant to tell you: Turns out that Krusty is one of the biggest tax cheats in history. And they nailed him, all thanks to you.",
    "directions": [],
    "raw_quote": " Sorry, the bank is close-- Oh, kid, gosh, I meant to tell you: Turns out that Krusty is one of the biggest tax cheats in history. And they nailed him, all thanks to you."
  },
  {
    "timecode": "",
    "speaker": "Bart Simpson",
    "quote": " ",
    "directions": [
      "GASP"
    ],
    "raw_quote": " (GASP)"
  },
  {
    "timecode": "05:54",
    "speaker": "Teller #2",
    "quote": " Some might say you're a hero, kid. Not me, however. I love Krusty.",
    "directions": [
      "BEAT"
    ],
    "raw_quote": " Some might say you're a hero, kid. (BEAT) Not me, however. I love Krusty."
  },
  {
    "timecode": "06:08",
    "speaker": "",
    "quote": "",
    "directions": [
      "Simpson Home: INT. SIMPSON HOUSE - TV ROOM - that evening"
    ],
    "raw_quote": "(Simpson Home: INT. SIMPSON HOUSE - TV ROOM - that evening)"
  },
  {
    "timecode": "06:08",
    "speaker": "Kent Brockman",
    "quote": " Ladies and gentlemen: Krusty the Clown!... was arrested today for massive tax fraud. Krusty's years of tax avoision would never have -- \"Avoision\" -- it's a crime. Look it up! ... would never have... I don't say \"evasion,\" I say \"avoision.\" ... would never have come to light if not for a crafty little boy named Bart Simpson.",
    "directions": [
      "BIG INTRO",
      "TOUCHES EARPHONE AND LOOKS O.S.",
      "THEN, BACK TO CAMERA",
      "TOUCHES EARPHONE AND LOOKS O.S. AGAIN, ANNOYED",
      "THEN, BACK TO CAMERA"
    ],
    "raw_quote": " (BIG INTRO) Ladies and gentlemen: Krusty the Clown!... was arrested today for massive tax fraud. Krusty's years of tax avoision would never have -- (TOUCHES EARPHONE AND LOOKS O.S.) \"Avoision\" -- it's a crime. Look it up! (THEN, BACK TO CAMERA) ... would never have... (TOUCHES EARPHONE AND LOOKS O.S. AGAIN, ANNOYED) I don't say \"evasion,\" I say \"avoision.\" (THEN, BACK TO CAMERA) ... would never have come to light if not for a crafty little boy named Bart Simpson."
  },
  {
    "timecode": "06:29",
    "speaker": "Bart Simpson",
    "quote": " Krusty's my hero! How could I do this to him?",
    "directions": [
      "DISMAYED"
    ],
    "raw_quote": " (DISMAYED) Krusty's my hero! How could I do this to him?"
  },
  {
    "timecode": "06:32",
    "speaker": "Lisa Simpson",
    "quote": " It is a tragedy for all us kids. But, Bart, you can't beat yourself up.",
    "directions": [],
    "raw_quote": " It is a tragedy for all us kids. But, Bart, you can't beat yourself up."
  },
  {
    "timecode": "06:36",
    "speaker": "Bart Simpson",
    "quote": " Yeah, there'll be enough people to do that for me at recess tomorrow.",
    "directions": [],
    "raw_quote": " Yeah, there'll be enough people to do that for me at recess tomorrow."
  },
  {
    "timecode": "06:44",
    "speaker": "",
    "quote": "",
    "directions": [
      "IRS Plaza: EXT. IRS plaza - THE NEXT DAY"
    ],
    "raw_quote": "(IRS Plaza: EXT. IRS plaza - THE NEXT DAY)"
  },
  {
    "timecode": "06:44",
    "speaker": "",
    "quote": "",
    "directions": [
      "IRS Building: INT. IRS BUILDING - OFFICE - SIMULTANEOUS"
    ],
    "raw_quote": "(IRS Building: INT. IRS BUILDING - OFFICE - SIMULTANEOUS)"
  },
  {
    "timecode": "06:44",
    "speaker": "Krusty the Clown",
    "quote": " Oh, I can't go to jail! I got a swanky lifestyle! I'm used to the best!",
    "directions": [
      "PLEADING"
    ],
    "raw_quote": " (PLEADING) Oh, I can't go to jail! I got a swanky lifestyle! I'm used to the best!"
  },
  {
    "timecode": "06:50",
    "speaker": "Chief Agent",
    "quote": " Krusty, this is America. We don't send our celebrities to jail. We're just going to garnish your salary.",
    "directions": [],
    "raw_quote": " Krusty, this is America. We don't send our celebrities to jail. We're just going to garnish your salary."
  },
  {
    "timecode": "06:55",
    "speaker": "Krusty the Clown",
    "quote": " Garnish my celery?",
    "directions": [],
    "raw_quote": " Garnish my celery?"
  },
  {
    "timecode": "06:57",
    "speaker": "Chief Agent",
    "quote": " Please Krusty, no jokes.",
    "directions": [],
    "raw_quote": " Please Krusty, no jokes."
  },
  {
    "timecode": "06:59",
    "speaker": "Krusty the Clown",
    "quote": " Who's joking?!! Oh, I don't know what you're saying! It all sounds so crazy to me!!",
    "directions": [
      "REALLY PANICKED, CONFUSED"
    ],
    "raw_quote": " (REALLY PANICKED, CONFUSED) Who's joking?!! Oh, I don't know what you're saying! It all sounds so crazy to me!!"
  },
  {
    "timecode": "07:05",
    "speaker": "2ND IRS AGENT",
    "quote": " It simply means we'll be taking part of your salary until your debt is repaid. Say 75% for forty years.",
    "directions": [
      "LOOKING AT FILE"
    ],
    "raw_quote": " It simply means we'll be taking part of your salary until your debt is repaid. (LOOKING AT FILE) Say 75% for forty years."
  },
  {
    "timecode": "07:12",
    "speaker": "Krusty the Clown",
    "quote": " But I don't plan to live that long!",
    "directions": [],
    "raw_quote": " But I don't plan to live that long!"
  },
  {
    "timecode": "07:13",
    "speaker": "Chief Agent",
    "quote": " Well, then, we'd better make it 95%.",
    "directions": [],
    "raw_quote": " Well, then, we'd better make it 95%."
  },
  {
    "timecode": "",
    "speaker": "Krusty the Clown",
    "quote": " ",
    "directions": [
      "GROAN"
    ],
    "raw_quote": " (GROAN)"
  },
  {
    "timecode": "07:17",
    "speaker": "",
    "quote": "",
    "directions": [
      "Simpson Home: Int. Simpson house - living room - later"
    ],
    "raw_quote": "(Simpson Home: Int. Simpson house - living room - later)"
  },
  {
    "timecode": "07:17",
    "speaker": "Announcer",
    "quote": " The Internal Revenue Service presents Herschel Krustofsky's Clown-related Entertainment Show.",
    "directions": [],
    "raw_quote": " The Internal Revenue Service presents Herschel Krustofsky's Clown-related Entertainment Show."
  },
  {
    "timecode": "07:17",
    "speaker": "Krusty the Clown",
    "quote": " Hey, hey, kids! Now that the Feds are calling the shots, this show's gotta be a lot more cost-effective. So we had to cut down on the frills -- like sets, props, costumes, and Sideshow Mel. But that doesn't mean we can't have fun. For example... I sure wish somebody would give me a banana cream pie... Yeah?!...",
    "directions": [
      "KRUSTY CHUCKLE",
      "CLOSES EYES, LICKS LIPS"
    ],
    "raw_quote": " (KRUSTY CHUCKLE) Hey, hey, kids! Now that the Feds are calling the shots, this show's gotta be a lot more cost-effective. So we had to cut down on the frills -- like sets, props, costumes, and Sideshow Mel. But that doesn't mean we can't have fun. For example... (CLOSES EYES, LICKS LIPS) I sure wish somebody would give me a banana cream pie... Yeah?!..."
  },
  {
    "timecode": "07:47",
    "speaker": "Krusty the Clown",
    "quote": " I guess we can't afford pies right now. Well, throw something!",
    "directions": [],
    "raw_quote": " I guess we can't afford pies right now. Well, throw something!"
  },
  {
    "timecode": "",
    "speaker": "Krusty the Clown",
    "quote": " ",
    "directions": [
      "KRUSTY GROAN"
    ],
    "raw_quote": " (KRUSTY GROAN)"
  },
  {
    "timecode": "08:02",
    "speaker": "",
    "quote": "",
    "directions": [
      "Krusty Burger: EXT. KRUSTY BURGER - the next day"
    ],
    "raw_quote": "(Krusty Burger: EXT. KRUSTY BURGER - the next day)"
  },
  {
    "timecode": "08:02",
    "speaker": "Homer Simpson",
    "quote": " Um, I'll have four Tax Burgers, one IRS-Wich -- withhold the lettuce -- three dependent-sized sodas and a FICAccino.",
    "directions": [],
    "raw_quote": " Um, I'll have four Tax Burgers, one IRS-Wich -- withhold the lettuce -- three dependent-sized sodas and a FICAccino."
  },
  {
    "timecode": "08:13",
    "speaker": "Squeaky-Voiced Teen",
    "quote": " Fill out schedule B. You should receive your burgers in six to eight weeks.",
    "directions": [],
    "raw_quote": " Fill out schedule B. You should receive your burgers in six to eight weeks."
  },
  {
    "timecode": "08:25",
    "speaker": "Homer Simpson",
    "quote": " Hey Marge -- what were your gambling losses last year?",
    "directions": [
      "CALLING OUT"
    ],
    "raw_quote": " (CALLING OUT) Hey Marge -- what were your gambling losses last year?"
  },
  {
    "timecode": "08:28",
    "speaker": "Marge Simpson",
    "quote": " Seven hundred dollars.",
    "directions": [
      "CALLING OUT"
    ],
    "raw_quote": " (CALLING OUT) Seven hundred dollars."
  },
  {
    "timecode": "08:33",
    "speaker": "",
    "quote": "",
    "directions": [
      "Krusty's Street: Ext. Krusty's street - bus stop - later"
    ],
    "raw_quote": "(Krusty's Street: Ext. Krusty's street - bus stop - later)"
  },
  {
    "timecode": "08:33",
    "speaker": "Krusty the Clown",
    "quote": " They took my money, they wrecked my show, they buried a bunch of stinking veterans in my family plot -- but at least I still got my memories. Those are locked up safe in my fabulous mansion.",
    "directions": [],
    "raw_quote": " They took my money, they wrecked my show, they buried a bunch of stinking veterans in my family plot -- but at least I still got my memories. Those are locked up safe in my fabulous mansion."
  },
  {
    "timecode": "08:47",
    "speaker": "",
    "quote": "",
    "directions": [
      "Krusty's Mansion: INT. KRUSTY'S mansion - CONTINUOUS"
    ],
    "raw_quote": "(Krusty's Mansion: INT. KRUSTY'S mansion - CONTINUOUS)"
  },
  {
    "timecode": "08:47",
    "speaker": "Auctioneer",
    "quote": " And now lot number 66: a handmade leather suitcase. Carried by the Krustofsky family upon their arrival at Ellis Island in 1902. A priceless heirloom and historic piece of Krustiana. What am I bid?",
    "directions": [],
    "raw_quote": " And now lot number 66: a handmade leather suitcase. Carried by the Krustofsky family upon their arrival at Ellis Island in 1902. A priceless heirloom and historic piece of Krustiana. What am I bid?"
  },
  {
    "timecode": "08:58",
    "speaker": "Selma Bouvier",
    "quote": " 40 cents!",
    "directions": [],
    "raw_quote": " 40 cents!"
  },
  {
    "timecode": "08:59",
    "speaker": "Auctioneer",
    "quote": " I got 40 cents... Sold for 40 cents!",
    "directions": [
      "RAPID-FIRE AUCTIONEER GIBBERISH, THEN BANGS GAVEL"
    ],
    "raw_quote": " I got 40 cents... (RAPID-FIRE AUCTIONEER GIBBERISH, THEN BANGS GAVEL) Sold for 40 cents!"
  },
  {
    "timecode": "09:08",
    "speaker": "Krusty the Clown",
    "quote": " 40 cents? Ach, my Grampa Zev would turn over in his grave if it wasn't filled with some veteran!",
    "directions": [],
    "raw_quote": " 40 cents? Ach, my Grampa Zev would turn over in his grave if it wasn't filled with some veteran!"
  },
  {
    "timecode": "09:15",
    "speaker": "Auctioneer",
    "quote": " Lot 67: 32 cartons of pornography.",
    "directions": [],
    "raw_quote": " Lot 67: 32 cartons of pornography."
  },
  {
    "timecode": "09:18",
    "speaker": "Jasper Beardly",
    "quote": " 10 cents!",
    "directions": [],
    "raw_quote": " 10 cents!"
  },
  {
    "timecode": "09:18",
    "speaker": "Phone Bid Taker",
    "quote": " 12!",
    "directions": [],
    "raw_quote": " 12!"
  },
  {
    "timecode": "09:20",
    "speaker": "Auctioneer",
    "quote": " 12 cents to our phone bidder in Japan. Any advance?",
    "directions": [],
    "raw_quote": " 12 cents to our phone bidder in Japan. Any advance?"
  },
  {
    "timecode": "09:23",
    "speaker": "Jasper Beardly",
    "quote": " All I brought is a dime. I didn't know there'd be pornography.",
    "directions": [],
    "raw_quote": " All I brought is a dime. I didn't know there'd be pornography."
  },
  {
    "timecode": "09:27",
    "speaker": "Auctioneer",
    "quote": " Sold for 12 cents.",
    "directions": [
      "BANGS GAVEL"
    ],
    "raw_quote": " (BANGS GAVEL) Sold for 12 cents."
  },
  {
    "timecode": "09:29",
    "speaker": "Krusty the Clown",
    "quote": " Oh, my beloved pornography! I can't watch this anymore. I'm going to bed.",
    "directions": [],
    "raw_quote": " Oh, my beloved pornography! I can't watch this anymore. I'm going to bed."
  },
  {
    "timecode": "09:34",
    "speaker": "Auctioneer",
    "quote": " How much for Krusty's bed?",
    "directions": [],
    "raw_quote": " How much for Krusty's bed?"
  },
  {
    "timecode": "09:36",
    "speaker": "Moe Szyslak",
    "quote": " Half a buck!",
    "directions": [],
    "raw_quote": " Half a buck!"
  },
  {
    "timecode": "09:36",
    "speaker": "Auctioneer",
    "quote": " Sold.",
    "directions": [
      "BANGS GAVEL"
    ],
    "raw_quote": " (BANGS GAVEL) Sold."
  },
  {
    "timecode": "09:37",
    "speaker": "Moe Szyslak",
    "quote": " Goodnight, everybody!",
    "directions": [],
    "raw_quote": " Goodnight, everybody!"
  },
  {
    "timecode": "09:39",
    "speaker": "All",
    "quote": " Goodnight, Moe!",
    "directions": [],
    "raw_quote": " Goodnight, Moe!"
  },
  {
    "timecode": "",
    "speaker": "Krusty the Clown",
    "quote": " ",
    "directions": [
      "UNHAPPY SOUND"
    ],
    "raw_quote": " (UNHAPPY SOUND)"
  },
  {
    "timecode": "09:42",
    "speaker": "",
    "quote": "",
    "directions": [
      "Krusty's House: Int. Krusty's house - SAME ROOM - later"
    ],
    "raw_quote": "(Krusty's House: Int. Krusty's house - SAME ROOM - later)"
  },
  {
    "timecode": "09:42",
    "speaker": "Auctioneer",
    "quote": " And now, lot 2,380: Krusty's private plane, the \"I'M-ON-A-ROLLA GAY.\"",
    "directions": [],
    "raw_quote": " And now, lot 2,380: Krusty's private plane, the \"I'M-ON-A-ROLLA GAY.\""
  },
  {
    "timecode": "09:46",
    "speaker": "Krusty the Clown",
    "quote": " But I love that plane! I used to fly to Vegas in it with Dean Martin. One night he looked out the window and the moon hit his eye like a big pizza pie. We wrote a song about it, but it ended up infringing on one he recorded years before.",
    "directions": [],
    "raw_quote": " But I love that plane! I used to fly to Vegas in it with Dean Martin. One night he looked out the window and the moon hit his eye like a big pizza pie. We wrote a song about it, but it ended up infringing on one he recorded years before."
  },
  {
    "timecode": "10:00",
    "speaker": "Patty Bouvier",
    "quote": " Hey, Selma, that plane would go great with your new suitcase.",
    "directions": [],
    "raw_quote": " Hey, Selma, that plane would go great with your new suitcase."
  },
  {
    "timecode": "10:04",
    "speaker": "Selma Bouvier",
    "quote": " Nah. I just bought it to soak my feet in.",
    "directions": [],
    "raw_quote": " Nah. I just bought it to soak my feet in."
  },
  {
    "timecode": "",
    "speaker": "Selma Bouvier",
    "quote": " ",
    "directions": [
      "MOAN OF PLEASURE"
    ],
    "raw_quote": " (MOAN OF PLEASURE)"
  },
  {
    "timecode": "10:16",
    "speaker": "Bart Simpson",
    "quote": " Krusty? Hi. Is it okay if I sit down here?",
    "directions": [],
    "raw_quote": " Krusty? Hi. Is it okay if I sit down here?"
  },
  {
    "timecode": "10:19",
    "speaker": "Krusty the Clown",
    "quote": " Go ahead, kid. Knock yourself out.",
    "directions": [],
    "raw_quote": " Go ahead, kid. Knock yourself out."
  },
  {
    "timecode": "10:22",
    "speaker": "Bart Simpson",
    "quote": " I'm sorry for all the trouble I've caused you, Krusty. But, you know, my mom says God never closes a door without opening a window.",
    "directions": [],
    "raw_quote": " I'm sorry for all the trouble I've caused you, Krusty. But, you know, my mom says God never closes a door without opening a window."
  },
  {
    "timecode": "10:29",
    "speaker": "Krusty the Clown",
    "quote": " No offense, kid, but your mom's a dingbat. There's no silver lining here. I was a big cheese -- a huge cheese! But now look at me! I gotta ride the bus like a schnook! I gotta live in an apartment like an idiot! I gotta wait in line with nobodies to buy groceries from a failure!",
    "directions": [],
    "raw_quote": " No offense, kid, but your mom's a dingbat. There's no silver lining here. I was a big cheese -- a huge cheese! But now look at me! I gotta ride the bus like a schnook! I gotta live in an apartment like an idiot! I gotta wait in line with nobodies to buy groceries from a failure!"
  },
  {
    "timecode": "10:50",
    "speaker": "Bart Simpson",
    "quote": " It doesn't matter how you live or what you did wrong. As long as you're on TV, people will respect you.",
    "directions": [],
    "raw_quote": " It doesn't matter how you live or what you did wrong. As long as you're on TV, people will respect you."
  },
  {
    "timecode": "10:55",
    "speaker": "Krusty the Clown",
    "quote": " Respect?! What good is respect without the moolah to back it up? Everywhere I go I see teachers in Ferraris, research scientists drinking champagne. I tried to drink a Coke on the bus and they took away my pass! That's no life for a famous clown!",
    "directions": [
      "SPITS RUDELY",
      "SADLY",
      "THROWS BOTTLE"
    ],
    "raw_quote": " Respect?! (SPITS RUDELY) What good is respect without the moolah to back it up? (SADLY) Everywhere I go I see teachers in Ferraris, research scientists drinking champagne. I tried to drink a Coke on the bus and they (THROWS BOTTLE) took away my pass! That's no life for a famous clown!"
  },
  {
    "timecode": "11:14",
    "speaker": "Bart Simpson",
    "quote": " Well, if it'll make you feel any better, Krusty, you can punch me in the face.",
    "directions": [],
    "raw_quote": " Well, if it'll make you feel any better, Krusty, you can punch me in the face."
  },
  {
    "timecode": "11:20",
    "speaker": "Krusty the Clown",
    "quote": " Nah, forget it. Go home, kid.",
    "directions": [],
    "raw_quote": " Nah, forget it. Go home, kid."
  },
  {
    "timecode": "11:29",
    "speaker": "",
    "quote": "",
    "directions": [
      "Kwik-E-Mart: ext. KWIK-E-MART - THAT NIGHT"
    ],
    "raw_quote": "(Kwik-E-Mart: ext. KWIK-E-MART - THAT NIGHT)"
  },
  {
    "timecode": "11:29",
    "speaker": "Apu Nahasapeemapetilon",
    "quote": " Shiva H. Vishnu! Where is that noise coming from?",
    "directions": [],
    "raw_quote": " Shiva H. Vishnu! Where is that noise coming from?"
  },
  {
    "timecode": "",
    "speaker": "Krusty the Clown",
    "quote": " ",
    "directions": [
      "LONG CRYING NOISE"
    ],
    "raw_quote": " (LONG CRYING NOISE)"
  },
  {
    "timecode": "11:37",
    "speaker": "",
    "quote": "",
    "directions": [
      "Skinner Home: EXT. SKINNER HOME - STREET - A FEW SECONDS LATER"
    ],
    "raw_quote": "(Skinner Home: EXT. SKINNER HOME - STREET - A FEW SECONDS LATER)"
  },
  {
    "timecode": "11:37",
    "speaker": "Man's Voice",
    "quote": " I must say, I've had a lovely evening, Agnes. I don't suppose I could come in for a cup of--",
    "directions": [],
    "raw_quote": " I must say, I've had a lovely evening, Agnes. I don't suppose I could come in for a cup of--"
  },
  {
    "timecode": "11:43",
    "speaker": "Agnes Skinner",
    "quote": " Seymour!",
    "directions": [],
    "raw_quote": " Seymour!"
  },
  {
    "timecode": "11:44",
    "speaker": "Seymour Skinner",
    "quote": " Mother?! Superintendent Chalmers?!!",
    "directions": [
      "THEN, SEES ESCORT"
    ],
    "raw_quote": " Mother?! (THEN, SEES ESCORT) Superintendent Chalmers?!!"
  },
  {
    "timecode": "11:46",
    "speaker": "Gary Chalmers",
    "quote": " Skinner!",
    "directions": [],
    "raw_quote": " Skinner!"
  },
  {
    "timecode": "11:47",
    "speaker": "Seymour Skinner",
    "quote": " What I wouldn't give for something to interrupt this awkward moment.",
    "directions": [
      "BEAT"
    ],
    "raw_quote": " (BEAT) What I wouldn't give for something to interrupt this awkward moment."
  },
  {
    "timecode": "",
    "speaker": "Krusty the Clown",
    "quote": " ",
    "directions": [
      "CRYING NOISE"
    ],
    "raw_quote": " (CRYING NOISE)"
  },
  {
    "timecode": "11:54",
    "speaker": "Seymour Skinner",
    "quote": " That'll do nicely.",
    "directions": [],
    "raw_quote": " That'll do nicely."
  },
  {
    "timecode": "12:01",
    "speaker": "",
    "quote": "",
    "directions": [
      "Simpson Home: Ext. Simpson house - a few seconds later"
    ],
    "raw_quote": "(Simpson Home: Ext. Simpson house - a few seconds later)"
  },
  {
    "timecode": "",
    "speaker": "Krusty the Clown",
    "quote": " ",
    "directions": [
      "LOOP-DE-LOOP CRYING SOUND"
    ],
    "raw_quote": " (LOOP-DE-LOOP CRYING SOUND)"
  },
  {
    "timecode": "12:01",
    "speaker": "Lisa Simpson",
    "quote": " You gotta hand it to Krusty.",
    "directions": [],
    "raw_quote": " You gotta hand it to Krusty."
  },
  {
    "timecode": "12:02",
    "speaker": "Homer Simpson",
    "quote": " Yeah, even with all his problems, he's still willing to do something unbelievably dangerous just to entertain his fans.",
    "directions": [],
    "raw_quote": " Yeah, even with all his problems, he's still willing to do something unbelievably dangerous just to entertain his fans."
  },
  {
    "timecode": "12:10",
    "speaker": "Homer Simpson",
    "quote": " Wow.",
    "directions": [
      "WATCHING KRUSTY, AWED"
    ],
    "raw_quote": " (WATCHING KRUSTY, AWED) Wow."
  },
  {
    "timecode": "12:10",
    "speaker": "Bart Simpson",
    "quote": " Aw, that's my Krusty. I got a feeling he'll be allll-right.",
    "directions": [],
    "raw_quote": " Aw, that's my Krusty. I got a feeling he'll be allll-right."
  },
  {
    "timecode": "12:26",
    "speaker": "",
    "quote": "",
    "directions": [
      "Base Of Mountain: EXT. BASE OF MOUNTAIN - a little later"
    ],
    "raw_quote": "(Base Of Mountain: EXT. BASE OF MOUNTAIN - a little later)"
  },
  {
    "timecode": "12:26",
    "speaker": "Lisa Simpson",
    "quote": " Oh my God! Krusty's shoes!",
    "directions": [
      "HORRIFIED"
    ],
    "raw_quote": " (HORRIFIED) Oh my God! Krusty's shoes!"
  },
  {
    "timecode": "12:29",
    "speaker": "Chief Wiggum",
    "quote": " Okay, folks, show's over. Nothing to see here, show's... Oh my God! A horrible plane crash! Hey everybody, get a load of this flaming wreckage! Come on, crowd around, crowd around! Don't be shy, crowd around!",
    "directions": [
      "THEN, SEEING WRECKAGE"
    ],
    "raw_quote": " Okay, folks, show's over. Nothing to see here, show's... (THEN, SEEING WRECKAGE) Oh my God! A horrible plane crash! Hey everybody, get a load of this flaming wreckage! Come on, crowd around, crowd around! Don't be shy, crowd around!"
  },
  {
    "timecode": "12:44",
    "speaker": "Chief Wiggum",
    "quote": " Ladies and gentlemen... Krusty the Clown is dead!",
    "directions": [
      "SOMBER"
    ],
    "raw_quote": " (SOMBER) Ladies and gentlemen... Krusty the Clown is dead!"
  },
  {
    "timecode": "12:58",
    "speaker": "",
    "quote": "",
    "directions": [
      "Springfield Cemetery: EXT. SPRINGFIELD CEMETERY - THE NEXT DAY"
    ],
    "raw_quote": "(Springfield Cemetery: EXT. SPRINGFIELD CEMETERY - THE NEXT DAY)"
  },
  {
    "timecode": "12:58",
    "speaker": "Bart Simpson",
    "quote": " I can't believe Krusty is really gone.",
    "directions": [],
    "raw_quote": " I can't believe Krusty is really gone."
  },
  {
    "timecode": "13:00",
    "speaker": "Homer Simpson",
    "quote": " Don't worry, son. I'm sure he's up in Heaven right now, laughing it up with all the other celebrities -- John Dillinger, Ty Cobb, Joseph Stalin... I wish I were dead.",
    "directions": [
      "SIGHS WISTFULLY"
    ],
    "raw_quote": " Don't worry, son. I'm sure he's up in Heaven right now, laughing it up with all the other celebrities -- John Dillinger, Ty Cobb, Joseph Stalin... (SIGHS WISTFULLY) I wish I were dead."
  },
  {
    "timecode": "13:15",
    "speaker": "Troy McClure",
    "quote": " We're gathered to mourn the passing of Herschel Shmoikel Krustofsky, beloved entertainer and dear friend. Hello, I'm Troy McClure. You might remember me from such show business funerals as \"Andre the Giant, We Hardly Knew Ye,\" and \"Shemp Howard: Today We Mourn a Stooge.\" Now... Krusty's closest friend and sidekick, Sideshow Mel.",
    "directions": [
      "VERY SOMBER",
      "NORMAL SLICK VOICE"
    ],
    "raw_quote": " (VERY SOMBER) We're gathered to mourn the passing of Herschel Shmoikel Krustofsky, beloved entertainer and dear friend. (NORMAL SLICK VOICE) Hello, I'm Troy McClure. You might remember me from such show business funerals as \"Andre the Giant, We Hardly Knew Ye,\" and \"Shemp Howard: Today We Mourn a Stooge.\" Now... Krusty's closest friend and sidekick, Sideshow Mel."
  },
  {
    "timecode": "13:37",
    "speaker": "Sideshow Mel",
    "quote": " I'll miss you, Krusty -- I and all the other Sideshows... except Sideshow Bob. But in the midst of our sorrow, we can take comfort in the fact that your elevated blood alcohol level probably helped you burn up quicker. Since you left us no earthly remains, it is my sad duty to unveil this simple memorial.",
    "directions": [],
    "raw_quote": " I'll miss you, Krusty -- I and all the other Sideshows... except Sideshow Bob. But in the midst of our sorrow, we can take comfort in the fact that your elevated blood alcohol level probably helped you burn up quicker. Since you left us no earthly remains, it is my sad duty to unveil this simple memorial."
  },
  {
    "timecode": "14:02",
    "speaker": "Troy McClure",
    "quote": " Next in our cavalcade of celebrity mourners: Bob Newhart.",
    "directions": [],
    "raw_quote": " Next in our cavalcade of celebrity mourners: Bob Newhart."
  },
  {
    "timecode": "14:11",
    "speaker": "Bob Newhart",
    "quote": " See... to tell you the truth, I'm just... I'm killing time here, I was waiting for uh, for a different funeral to start.",
    "directions": [
      "LOW"
    ],
    "raw_quote": " (LOW) See... to tell you the truth, I'm just... I'm killing time here, I was waiting for uh, for a different funeral to start."
  },
  {
    "timecode": "14:21",
    "speaker": "Troy McClure",
    "quote": " I'll handle it. Bob Newhart everybody!",
    "directions": [
      "REASSURING",
      "TO CROWD"
    ],
    "raw_quote": " (REASSURING) I'll handle it. (TO CROWD) Bob Newhart everybody!"
  },
  {
    "timecode": "14:27",
    "speaker": "Bob Newhart",
    "quote": " Uh... um, though I started my career several years before uh, Krusty, so I could never really have learned anything directly from him, still... I think... in a way, in a very meaningful way, that I... all of us... have learned from him. in that is... by being a clown on television for so many years... even though you know, many of us, we didn't watch his show... Thank you.",
    "directions": [
      "AWKWARDLY THROUGHOUT",
      "BEAT",
      "BEAT",
      "COUGH",
      "BEAT"
    ],
    "raw_quote": " (AWKWARDLY THROUGHOUT) Uh... um, though I started my career several years before uh, Krusty, so I could never really have learned anything directly from him, still... I think... in a way, in a very meaningful way, that I... all of us... have learned from him. (BEAT) in that is... by being a clown on television for so many years... even though you know, many of us, we didn't watch his show... (BEAT) (COUGH) (BEAT) Thank you."
  },
  {
    "timecode": "15:12",
    "speaker": "Troy McClure",
    "quote": " Well, that's the funeral, folks. We'll be sitting shiva at the Friar's Club at 7 p.m. and again at 10. You must be over 18 for the 10 o'clock -- It gets a little blue.",
    "directions": [
      "SLY"
    ],
    "raw_quote": " Well, that's the funeral, folks. We'll be sitting shiva at the Friar's Club at 7 p.m. and again at 10. You must be over 18 for the 10 o'clock -- (SLY) It gets a little blue."
  },
  {
    "timecode": "15:29",
    "speaker": "",
    "quote": "",
    "directions": [
      "Simpson Home: INT. SIMPSON HOME - LIVING ROOM - LATER THAT DAY"
    ],
    "raw_quote": "(Simpson Home: INT. SIMPSON HOME - LIVING ROOM - LATER THAT DAY)"
  },
  {
    "timecode": "15:29",
    "speaker": "Kent Brockman",
    "quote": " And so Herschel Krustofsky is gone. But not forgotten. Today was the unveiling of the new Krusty stamp. Postal patrons were asked to choose between two competing designs: One of Krusty's heartwarming smile... and one of his fiery death.",
    "directions": [
      "BRIGHTENS"
    ],
    "raw_quote": " And so Herschel Krustofsky is gone. (BRIGHTENS) But not forgotten. Today was the unveiling of the new Krusty stamp. Postal patrons were asked to choose between two competing designs: One of Krusty's heartwarming smile... and one of his fiery death."
  },
  {
    "timecode": "15:44",
    "speaker": "Kent Brockman",
    "quote": " By a nearly 2 to 1 vote, the smiling Krusty was chosen.",
    "directions": [],
    "raw_quote": " By a nearly 2 to 1 vote, the smiling Krusty was chosen."
  },
  {
    "timecode": "15:55",
    "speaker": "",
    "quote": "",
    "directions": [
      "Simpson Home: INT. SIMPSON HOUSE - BART'S ROOM - LATER"
    ],
    "raw_quote": "(Simpson Home: INT. SIMPSON HOUSE - BART'S ROOM - LATER)"
  },
  {
    "timecode": "15:55",
    "speaker": "Homer Simpson",
    "quote": " Don't let Krusty's death get you down, boy. People die all the time. Just like that. Why, you could wake up dead tomorrow. Well, good night.",
    "directions": [
      "SWEETLY",
      "SNAPS FINGERS ONCE",
      "BEAT"
    ],
    "raw_quote": " (SWEETLY) Don't let Krusty's death get you down, boy. People die all the time. Just like that. (SNAPS FINGERS ONCE) Why, you could wake up dead tomorrow. (BEAT) Well, good night."
  },
  {
    "timecode": "16:17",
    "speaker": "Bart Simpson",
    "quote": " Krusty!",
    "directions": [
      "GASP"
    ],
    "raw_quote": " (GASP) Krusty!"
  },
  {
    "timecode": "16:20",
    "speaker": "Bart Simpson",
    "quote": " Mom! I just saw Krusty!",
    "directions": [],
    "raw_quote": " Mom! I just saw Krusty!"
  },
  {
    "timecode": "16:21",
    "speaker": "Marge Simpson",
    "quote": " Yes, dear. In your mind.",
    "directions": [
      "UNDERSTANDINGLY"
    ],
    "raw_quote": " (UNDERSTANDINGLY) Yes, dear. In your mind."
  },
  {
    "timecode": "16:23",
    "speaker": "Bart Simpson",
    "quote": " No, on the street.",
    "directions": [],
    "raw_quote": " No, on the street."
  },
  {
    "timecode": "16:24",
    "speaker": "Marge Simpson",
    "quote": " On the street in your mind.",
    "directions": [
      "UNDERSTANDINGLY"
    ],
    "raw_quote": " (UNDERSTANDINGLY) On the street in your mind."
  },
  {
    "timecode": "16:26",
    "speaker": "Bart Simpson",
    "quote": " Why won't you believe me?!",
    "directions": [],
    "raw_quote": " Why won't you believe me?!"
  },
  {
    "timecode": "16:27",
    "speaker": "Marge Simpson",
    "quote": " Sweetheart, maybe you just want Krusty to be alive so badly, you think you see him everywhere. I went through the same thing when Lyndon Johnson died.",
    "directions": [],
    "raw_quote": " Sweetheart, maybe you just want Krusty to be alive so badly, you think you see him everywhere. I went through the same thing when Lyndon Johnson died."
  },
  {
    "timecode": "16:37",
    "speaker": "",
    "quote": "",
    "directions": [
      "Dr. Hibbert's Office: Int. Dr. Hibbert's office - waiting room - continuous"
    ],
    "raw_quote": "(Dr. Hibbert's Office: Int. Dr. Hibbert's office - waiting room - continuous)"
  },
  {
    "timecode": "16:37",
    "speaker": "Dr. Julius Hibbert",
    "quote": " ...and these pills will help with the queasiness.",
    "directions": [],
    "raw_quote": " ...and these pills will help with the queasiness."
  },
  {
    "timecode": "16:43",
    "speaker": "Bart Simpson",
    "quote": " Krusty?! Doctor Hibbert, who was that man?",
    "directions": [],
    "raw_quote": " Krusty?! Doctor Hibbert, who was that man?"
  },
  {
    "timecode": "16:46",
    "speaker": "Dr. Julius Hibbert",
    "quote": " Now Bart, telling you would violate the patient/doctor privilege, just as if I were to tell you that Jaspser here has five seconds to live.",
    "directions": [
      "CHUCKLES, CHIPPER"
    ],
    "raw_quote": " (CHUCKLES, CHIPPER) Now Bart, telling you would violate the patient/doctor privilege, just as if I were to tell you that Jaspser here has five seconds to live."
  },
  {
    "timecode": "16:55",
    "speaker": "Jasper Beardly",
    "quote": " What'd he say?",
    "directions": [
      "DIDN'T HEAR"
    ],
    "raw_quote": " (DIDN'T HEAR) What'd he say?"
  },
  {
    "timecode": "16:56",
    "speaker": "Mrs. Glick",
    "quote": " He said I'm next!",
    "directions": [
      "OFFICIOUS"
    ],
    "raw_quote": " (OFFICIOUS) He said I'm next!"
  },
  {
    "timecode": "16:59",
    "speaker": "",
    "quote": "",
    "directions": [
      "SPRINGFIELD SHORES: Ext. Springfield Shores - later"
    ],
    "raw_quote": "(SPRINGFIELD SHORES: Ext. Springfield Shores - later)"
  },
  {
    "timecode": "16:59",
    "speaker": "Bart Simpson",
    "quote": " Am I going crazy? I'm seeing Krusty everywhere.",
    "directions": [],
    "raw_quote": " Am I going crazy? I'm seeing Krusty everywhere."
  },
  {
    "timecode": "17:13",
    "speaker": "",
    "quote": "",
    "directions": [
      "Simpson Home: Int. Simpson house - Lisa's Bedroom"
    ],
    "raw_quote": "(Simpson Home: Int. Simpson house - Lisa's Bedroom)"
  },
  {
    "timecode": "17:13",
    "speaker": "Lisa Simpson",
    "quote": " Bart, you're seeing Krusty everywhere because you want to tell him you're sorry for causing his death. Would it help if I told you you're not responsible for Krusty's death?",
    "directions": [],
    "raw_quote": " Bart, you're seeing Krusty everywhere because you want to tell him you're sorry for causing his death. Would it help if I told you you're not responsible for Krusty's death?"
  },
  {
    "timecode": "17:21",
    "speaker": "Bart Simpson",
    "quote": " Yes. Yes it would.",
    "directions": [],
    "raw_quote": " Yes. Yes it would."
  },
  {
    "timecode": "17:22",
    "speaker": "Lisa Simpson",
    "quote": " Well I can't. You'll just have to learn to live with your mental problem.",
    "directions": [],
    "raw_quote": " Well I can't. You'll just have to learn to live with your mental problem."
  },
  {
    "timecode": "17:25",
    "speaker": "Bart Simpson",
    "quote": " Wait a minute! All those things I saw -- there's a connection! The truck full of nets and buckets, the queasy guy, the lobsters... they all point to one thing. Follow me.",
    "directions": [
      "SUDDEN REALIZATION",
      "DRAMATICALLY"
    ],
    "raw_quote": " (SUDDEN REALIZATION) Wait a minute! All those things I saw -- there's a connection! The truck full of nets and buckets, the queasy guy, the lobsters... they all point to one thing. (DRAMATICALLY) Follow me."
  },
  {
    "timecode": "17:41",
    "speaker": "",
    "quote": "",
    "directions": [
      "SPRINGFIELD MARINA - BAIT & TACKLE SHOP: EXT. SPRINGFIELD MARINA - BAIT & TACKLE SHOP - CONTINUOUS"
    ],
    "raw_quote": "(SPRINGFIELD MARINA - BAIT & TACKLE SHOP: EXT. SPRINGFIELD MARINA - BAIT & TACKLE SHOP - CONTINUOUS)"
  },
  {
    "timecode": "17:41",
    "speaker": "",
    "quote": "",
    "directions": [
      "BAIT & TACKLE SHOP: INT. BAIT & TACKLE SHOP - CONTINUOUS"
    ],
    "raw_quote": "(BAIT & TACKLE SHOP: INT. BAIT & TACKLE SHOP - CONTINUOUS)"
  },
  {
    "timecode": "17:41",
    "speaker": "Captain Horatio McCallister",
    "quote": " Arrr, I've got some customers. Call me back, Ishmael. Ahoy there, minnows.",
    "directions": [
      "INTO PHONE",
      "HANGS UP PHONE"
    ],
    "raw_quote": " (INTO PHONE) Arrr, I've got some customers. Call me back, Ishmael. (HANGS UP PHONE) Ahoy there, minnows."
  },
  {
    "timecode": "17:47",
    "speaker": "Bart Simpson",
    "quote": " Ahoy! Have you seen this man?",
    "directions": [
      "HOLDING UP BALLOON"
    ],
    "raw_quote": " (HOLDING UP BALLOON) Ahoy! Have you seen this man?"
  },
  {
    "timecode": "17:52",
    "speaker": "Captain Horatio McCallister",
    "quote": " Arrr, that's Handsome Pete. He dances for nickels. Pete! Ye got some customers!",
    "directions": [
      "CALLING TO BACK ROOM"
    ],
    "raw_quote": " Arrr, that's Handsome Pete. He dances for nickels. (CALLING TO BACK ROOM) Pete! Ye got some customers!"
  },
  {
    "timecode": "18:03",
    "speaker": "Lisa Simpson",
    "quote": " No. We're looking for this man, Krusty the Clown.",
    "directions": [],
    "raw_quote": " No. We're looking for this man, Krusty the Clown."
  },
  {
    "timecode": "18:08",
    "speaker": "Captain Horatio McCallister",
    "quote": " Narrr, narrr, narrr.",
    "directions": [
      "SHAKING HIS HEAD"
    ],
    "raw_quote": " (SHAKING HIS HEAD) Narrr, narrr, narrr."
  },
  {
    "timecode": "18:10",
    "speaker": "Lisa Simpson",
    "quote": " It's hopeless, Bart. We've searched up and down these docks, from Pier One to that Pier 1 by Pier Seventeen.",
    "directions": [],
    "raw_quote": " It's hopeless, Bart. We've searched up and down these docks, from Pier One to that Pier 1 by Pier Seventeen."
  },
  {
    "timecode": "18:21",
    "speaker": "Bart Simpson",
    "quote": " Lisa! Look! A signature with stars around it, just like Krusty's!",
    "directions": [],
    "raw_quote": " Lisa! Look! A signature with stars around it, just like Krusty's!"
  },
  {
    "timecode": "18:25",
    "speaker": "Lisa Simpson",
    "quote": " \"Rory B. Bellows, Slip Eight!\" Let's go!",
    "directions": [
      "READING"
    ],
    "raw_quote": " (READING) \"Rory B. Bellows, Slip Eight!\" Let's go!"
  },
  {
    "timecode": "18:31",
    "speaker": "Captain Horatio McCallister",
    "quote": " Not a quarter!! Arrr, he'll be dancing for hours!",
    "directions": [],
    "raw_quote": " Not a quarter!! Arrr, he'll be dancing for hours!"
  },
  {
    "timecode": "18:40",
    "speaker": "",
    "quote": "",
    "directions": [
      "SPRINGFIELD MARINA - SLIP 8: EXT. SPRINGFIELD MARINA - SLIP 8 - A MINUTE LATER"
    ],
    "raw_quote": "(SPRINGFIELD MARINA - SLIP 8: EXT. SPRINGFIELD MARINA - SLIP 8 - A MINUTE LATER)"
  },
  {
    "timecode": "18:40",
    "speaker": "Bart Simpson",
    "quote": " Are you Rory B. Bellows?",
    "directions": [],
    "raw_quote": " Are you Rory B. Bellows?"
  },
  {
    "timecode": "18:41",
    "speaker": "Rory",
    "quote": " Yes.",
    "directions": [
      "UNGRAVELLY KRUSTY VOICE"
    ],
    "raw_quote": " (UNGRAVELLY KRUSTY VOICE) Yes."
  },
  {
    "timecode": "18:42",
    "speaker": "Bart Simpson",
    "quote": " How about Krusty the Clown?",
    "directions": [],
    "raw_quote": " How about Krusty the Clown?"
  },
  {
    "timecode": "18:45",
    "speaker": "Rory",
    "quote": " Sorry. I don't do impressions. ",
    "directions": [
      "RETURNS TO HIS WORK"
    ],
    "raw_quote": " Sorry. I don't do impressions. (RETURNS TO HIS WORK)"
  },
  {
    "timecode": "18:47",
    "speaker": "Bart Simpson",
    "quote": " Well, if you're not Krusty, how come you have the exact same signature as him?",
    "directions": [
      "HOLDING UP CHECK"
    ],
    "raw_quote": " (HOLDING UP CHECK) Well, if you're not Krusty, how come you have the exact same signature as him?"
  },
  {
    "timecode": "18:51",
    "speaker": "Rory",
    "quote": " I'm Rory Bellows, I tell you. And I've got a lot of corroborating evidence... over here... by the throttle.",
    "directions": [],
    "raw_quote": " I'm Rory Bellows, I tell you. And I've got a lot of corroborating evidence... over here... by the throttle."
  },
  {
    "timecode": "",
    "speaker": "Rory",
    "quote": " ",
    "directions": [
      "SATISFIED CHUCKLE"
    ],
    "raw_quote": " (SATISFIED CHUCKLE)"
  },
  {
    "timecode": "19:04",
    "speaker": "Rory",
    "quote": " You know, you two coulda said something 'steada letting me make an ass of myself.",
    "directions": [
      "RORY GROAN"
    ],
    "raw_quote": " (RORY GROAN) You know, you two coulda said something 'steada letting me make an ass of myself."
  },
  {
    "timecode": "19:09",
    "speaker": "Lisa Simpson",
    "quote": " Hey! You've got a pacemaker scar just like Krusty!",
    "directions": [],
    "raw_quote": " Hey! You've got a pacemaker scar just like Krusty!"
  },
  {
    "timecode": "19:12",
    "speaker": "Bart Simpson",
    "quote": " And Krusty's superfluous third nipple!",
    "directions": [],
    "raw_quote": " And Krusty's superfluous third nipple!"
  },
  {
    "timecode": "19:16",
    "speaker": "Rory",
    "quote": " Why won't you leave me alone, kid? Can't you see I don't want to be Krusty anymore? That's why I faked my death.",
    "directions": [
      "GROAN",
      "SIGHS, KRUSTY VOICE"
    ],
    "raw_quote": " (GROAN) Why won't you leave me alone, kid? (SIGHS, KRUSTY VOICE) Can't you see I don't want to be Krusty anymore? That's why I faked my death."
  },
  {
    "timecode": "19:21",
    "speaker": "Lisa Simpson",
    "quote": " But we saw your plane crash...",
    "directions": [],
    "raw_quote": " But we saw your plane crash..."
  },
  {
    "timecode": "19:23",
    "speaker": "Krusty the Clown",
    "quote": " Yeah, but I wasn't in it...",
    "directions": [],
    "raw_quote": " Yeah, but I wasn't in it..."
  },
  {
    "timecode": "19:25",
    "speaker": "Krusty the Clown",
    "quote": " Just before I hit the mountain, I jumped out of the plane into a carefully placed net.",
    "directions": [],
    "raw_quote": " Just before I hit the mountain, I jumped out of the plane into a carefully placed net."
  },
  {
    "timecode": "",
    "speaker": "Krusty the Clown",
    "quote": " ",
    "directions": [
      "KRUSTY GROAN"
    ],
    "raw_quote": " (KRUSTY GROAN)"
  },
  {
    "timecode": "19:33",
    "speaker": "Bart Simpson",
    "quote": " So now that we've blown your cover, I guess you've gotta come back and do your show again!",
    "directions": [
      "HOPEFUL"
    ],
    "raw_quote": " (HOPEFUL) So now that we've blown your cover, I guess you've gotta come back and do your show again!"
  },
  {
    "timecode": "19:37",
    "speaker": "Lisa Simpson",
    "quote": " Or kill us. ",
    "directions": [
      "NERVOUS GIGGLE"
    ],
    "raw_quote": " Or kill us. (NERVOUS GIGGLE)"
  },
  {
    "timecode": "",
    "speaker": "Bart Simpson",
    "quote": " ",
    "directions": [
      "NERVOUS GIGGLE"
    ],
    "raw_quote": " (NERVOUS GIGGLE)"
  },
  {
    "timecode": "19:39",
    "speaker": "Krusty the Clown",
    "quote": " I won't be coming back, kids. I've got a sweet life here. The sea air is clearing my lungs, the sun is toasting my pale skin a healthy brown, and most important, I learned that I don't need money to be happy. All that high living just distracted me from my true calling in life: salvaging sunken barges for scrap iron. Sorry, kids, there's nothing left for me on dry land anymore.",
    "directions": [],
    "raw_quote": " I won't be coming back, kids. I've got a sweet life here. The sea air is clearing my lungs, the sun is toasting my pale skin a healthy brown, and most important, I learned that I don't need money to be happy. All that high living just distracted me from my true calling in life: salvaging sunken barges for scrap iron. Sorry, kids, there's nothing left for me on dry land anymore."
  },
  {
    "timecode": "20:03",
    "speaker": "Bart Simpson",
    "quote": " But Krusty, what about all the kids who depend on you to brighten up their afternoons? Are you going to turn your back on them?",
    "directions": [],
    "raw_quote": " But Krusty, what about all the kids who depend on you to brighten up their afternoons? Are you going to turn your back on them?"
  },
  {
    "timecode": "20:10",
    "speaker": "Krusty the Clown",
    "quote": " Yes.",
    "directions": [
      "OVER HIS SHOULDER"
    ],
    "raw_quote": " (OVER HIS SHOULDER) Yes."
  },
  {
    "timecode": "20:14",
    "speaker": "Bart Simpson",
    "quote": " C'mon, Lis, Krusty doesn't want our attention anymore. Let's go worship somebody who has the guts to be a celebrity.",
    "directions": [],
    "raw_quote": " C'mon, Lis, Krusty doesn't want our attention anymore. Let's go worship somebody who has the guts to be a celebrity."
  },
  {
    "timecode": "20:20",
    "speaker": "Lisa Simpson",
    "quote": " Yeah, Krusty doesn't want to be a clown. He's happy just being another blue-collar bozo.",
    "directions": [],
    "raw_quote": " Yeah, Krusty doesn't want to be a clown. He's happy just being another blue-collar bozo."
  },
  {
    "timecode": "20:26",
    "speaker": "Krusty the Clown",
    "quote": " Meh.",
    "directions": [],
    "raw_quote": " Meh."
  },
  {
    "timecode": "20:28",
    "speaker": "Bart Simpson",
    "quote": " Krusty's tired of having phonies around, pretending to be his friends. I'm sure he'll find plenty of people who'll like him for who he is.",
    "directions": [
      "SO KRUSTY CAN HEAR"
    ],
    "raw_quote": " (SO KRUSTY CAN HEAR) Krusty's tired of having phonies around, pretending to be his friends. I'm sure he'll find plenty of people who'll like him for who he is."
  },
  {
    "timecode": "20:36",
    "speaker": "Krusty the Clown",
    "quote": " It could happen. Who needs friends? The incessant beep of the Global Positioning System is all the companionship I need.",
    "directions": [
      "UNSURE",
      "AFTER A BEAT"
    ],
    "raw_quote": " (UNSURE) It could happen. (AFTER A BEAT) Who needs friends? The incessant beep of the Global Positioning System is all the companionship I need."
  },
  {
    "timecode": "",
    "speaker": "GLOBAL POSITIONING SYSTEM",
    "quote": " ",
    "directions": [
      "STEADY SQUAWKING SOUND"
    ],
    "raw_quote": " (STEADY SQUAWKING SOUND)"
  },
  {
    "timecode": "",
    "speaker": "Krusty the Clown",
    "quote": " ",
    "directions": [
      "SCREAM"
    ],
    "raw_quote": " (SCREAM)"
  },
  {
    "timecode": "20:50",
    "speaker": "Krusty the Clown",
    "quote": " Tell me where you are now, you bastard!",
    "directions": [],
    "raw_quote": " Tell me where you are now, you bastard!"
  },
  {
    "timecode": "20:52",
    "speaker": "Krusty the Clown",
    "quote": " All right, I admit it. I miss the phonies -- but that's all I miss. That and the Shirley Jones/Marty Engles New Years Eve Party.",
    "directions": [
      "TURNS TO KIDS"
    ],
    "raw_quote": " (TURNS TO KIDS) All right, I admit it. I miss the phonies -- but that's all I miss. That and the Shirley Jones/Marty Engles New Years Eve Party."
  },
  {
    "timecode": "21:01",
    "speaker": "Lisa Simpson",
    "quote": " What about that great feeling you get from knowing you're better than regular people?",
    "directions": [],
    "raw_quote": " What about that great feeling you get from knowing you're better than regular people?"
  },
  {
    "timecode": "21:05",
    "speaker": "Bart Simpson",
    "quote": " What about: being an illiterate TV clown who's still more respected than all the scientists, doctors and educators in the country put together?",
    "directions": [
      "TRUMP CARD"
    ],
    "raw_quote": " (TRUMP CARD) What about: being an illiterate TV clown who's still more respected than all the scientists, doctors and educators in the country put together?"
  },
  {
    "timecode": "21:16",
    "speaker": "Krusty the Clown",
    "quote": " Yeahhhh, I'm not gonna let those guys hog all the respect while I'm out here on some stinkin' tub.",
    "directions": [],
    "raw_quote": " Yeahhhh, I'm not gonna let those guys hog all the respect while I'm out here on some stinkin' tub."
  },
  {
    "timecode": "21:24",
    "speaker": "Krusty the Clown",
    "quote": " That's just what those eggheads want. Well, forget it, Poindexter, 'cause Krusty's back in town!",
    "directions": [],
    "raw_quote": " That's just what those eggheads want. Well, forget it, Poindexter, 'cause Krusty's back in town!"
  },
  {
    "timecode": "21:38",
    "speaker": "Lisa Simpson",
    "quote": " Yay!",
    "directions": [],
    "raw_quote": " Yay!"
  },
  {
    "timecode": "21:38",
    "speaker": "",
    "quote": "",
    "directions": [
      "BEACH - A WHILE LATER: EXT. BEACH - A WHILE LATER"
    ],
    "raw_quote": "(BEACH - A WHILE LATER: EXT. BEACH - A WHILE LATER)"
  },
  {
    "timecode": "21:38",
    "speaker": "Bart Simpson",
    "quote": " So Krusty, what are you gonna do about your tax problem?",
    "directions": [],
    "raw_quote": " So Krusty, what are you gonna do about your tax problem?"
  },
  {
    "timecode": "21:42",
    "speaker": "Krusty the Clown",
    "quote": " Don't sweat it. The life of \"Rory B. Bellows\" is insured for a surprisingly large amount.",
    "directions": [],
    "raw_quote": " Don't sweat it. The life of \"Rory B. Bellows\" is insured for a surprisingly large amount."
  },
  {
    "timecode": "",
    "speaker": "Krusty the Clown",
    "quote": " ",
    "directions": [
      "LAUGHTER"
    ],
    "raw_quote": " (LAUGHTER)"
  }
]